MANIFEST.in
README.rst
broadcaster.py
requirements.txt
setup.py
live_thumb.egg-info/PKG-INFO
live_thumb.egg-info/SOURCES.txt
live_thumb.egg-info/dependency_links.txt
live_thumb.egg-info/entry_points.txt
live_thumb.egg-info/pbr.json
live_thumb.egg-info/requires.txt
live_thumb.egg-info/top_level.txt