Metadata-Version: 1.0
Name: live-thumb
Version: 0.1.7
Summary: MJPEG broadcaster
Home-page: UNKNOWN
Author: Globo.com
Author-email: UNKNOWN
License: UNKNOWN
Platform: UNKNOWN
